dama/__init__.py
dama/cli.py
dama/exceptions.py
dama/fmtypes.py
dama/ittools.py
dama/measures.py
dama/models.py
dama/processing.py
dama/random.py
dama/abc/__init__.py
dama/abc/data.py
dama/abc/driver.py
dama/abc/group.py
dama/ae/__init__.py
dama/ae/wrappers.py
dama/ae/extended/__init__.py
dama/ae/extended/w_keras.py
dama/clf/__init__.py
dama/clf/wrappers.py
dama/clf/extended/__init__.py
dama/clf/extended/w_keras.py
dama/clf/extended/w_lgb.py
dama/clf/extended/w_sklearn.py
dama/clf/extended/w_xgboost.py
dama/commands/__init__.py
dama/commands/config.py
dama/commands/dataset.py
dama/commands/models.py
dama/commands/plot.py
dama/commands/reader.py
dama/commands/repo.py
dama/config/settings.cfg.example
dama/data/__init__.py
dama/data/csv.py
dama/data/ds.py
dama/data/it.py
dama/data/web.py
dama/drivers/__init__.py
dama/drivers/core.py
dama/drivers/postgres.py
dama/drivers/sqlite.py
dama/groups/__init__.py
dama/groups/core.py
dama/groups/hdf5.py
dama/groups/postgres.py
dama/groups/sqlite.py
dama/groups/zarr.py
dama/reg/__init__.py
dama/reg/wrappers.py
dama/reg/extended/__init__.py
dama/reg/extended/w_lgb.py
dama/reg/extended/w_sklearn.py
dama/reg/extended/w_xgboost.py
dama/utils/__init__.py
dama/utils/config.py
dama/utils/core.py
dama/utils/decorators.py
dama/utils/files.py
dama/utils/logger.py
dama/utils/miscellaneous.py
dama/utils/model_selection.py
dama/utils/network.py
dama/utils/numeric_functions.py
dama/utils/order.py
dama/utils/seq.py
dama/utils/tf_functions.py
DaMa_ML-1.0a1.dist-info/LICENSE
DaMa_ML-1.0a1.dist-info/METADATA
DaMa_ML-1.0a1.dist-info/WHEEL
DaMa_ML-1.0a1.dist-info/entry_points.txt
DaMa_ML-1.0a1.dist-info/top_level.txt
DaMa_ML-1.0a1.dist-info/RECORD
