Metadata-Version: 2.1
Name: DaMa-ML
Version: 1.0a1
Summary: A framework for data management and is used to do data science and machine learning's pipelines
Home-page: https://github.com/elaeon/dama_ml
Author: Alejandro Martínez
Author-email: mara80@gmail.com
License: Apache
Keywords: data python management machine learning science
Platform: UNKNOWN
Classifier: Development Status :: 3 - Alpha
Classifier: License :: OSI Approved :: Apache Software License
Classifier: Programming Language :: Python :: 3.6
Requires-Dist: matplotlib (>=2.2)
Requires-Dist: networkx (>=1.11)
Requires-Dist: numpy (<=1.14.5)
Requires-Dist: pandas (>=0.19.2)
Requires-Dist: scikit-learn (>=0.18)
Requires-Dist: scipy (>=0.18.1)
Requires-Dist: tabulate (>=0.7.5)
Requires-Dist: tensorflow (>=1.0.1)
Requires-Dist: tqdm (>=4.11.2)
Requires-Dist: h5py (>=2.6.0)
Requires-Dist: xmltodict (>=0.10.2)
Requires-Dist: keras (>=2.0.2)
Requires-Dist: psycopg2 (>=2.7.3.2)
Requires-Dist: dask (>=0.18.2)
Requires-Dist: xarray (>=0.10.9)
Requires-Dist: zarr (>=2.2.0)
Requires-Dist: numcodecs (>=0.6.1)
Requires-Dist: toolz (>=0.9.0)
Requires-Dist: cytoolz (>=0.9.0.1)
Requires-Dist: msgpack-python (>=0.5.6)
Requires-Dist: scikit-image (>=0.14.0)
Requires-Dist: GitPython (>=2.1.11)
Requires-Dist: psutil (>=5.5.1)
Requires-Dist: colorlog (>=4.0.2)
Provides-Extra: docs
Requires-Dist: sphinx (>=1.4.0) ; extra == 'docs'
Provides-Extra: test
